README.md
setup.py
lquery/__init__.py
lquery/empty.py
lquery/func.py
lquery/iterable.py
lquery/queryable.py
lquery.egg-info/PKG-INFO
lquery.egg-info/SOURCES.txt
lquery.egg-info/dependency_links.txt
lquery.egg-info/not-zip-safe
lquery.egg-info/requires.txt
lquery.egg-info/top_level.txt
lquery/expr/__init__.py
lquery/expr/builder.py
lquery/expr/core.py
lquery/expr/emitter.py
lquery/expr/utils.py
lquery/expr/visitor.py
lquery/extras/__init__.py
lquery/extras/_common.py
lquery/extras/_common_visitor.py
lquery/extras/tinydb.py
lquery/extras/mongodb/__init__.py
lquery/extras/mongodb/core.py
lquery/extras/mongodb/options.py