Metadata-Version: 1.0
Name: lquery
Version: 0.1.1
Summary: UNKNOWN
Home-page: https://github.com/Cologler/lquery-python
Author: Cologler
Author-email: skyoflw@gmail.com
License: MIT License
Platform: UNKNOWN
